[
{
	"uri": "https://b-vwj.github.io/TheVue/school-notes/mathematics/college-algebra-and-trig/",
	"title": "College Algebra and Pre-calculus",
	"tags": [],
	"description": "",
	"content": " Algebra and Pre-calculus Notes: "
},
{
	"uri": "https://b-vwj.github.io/TheVue/school-notes/mathematics/college-algebra-and-trig/notes/chapter3_notes/",
	"title": "College Algebra and Pre-calculus Notes",
	"tags": [],
	"description": "College Algebra and Pre-calculus Notes",
	"content": " Notes: "
},
{
	"uri": "https://b-vwj.github.io/TheVue/school-notes/english/",
	"title": "English Notes",
	"tags": [],
	"description": "",
	"content": " L\u0026rsquo;Anglais Welcome to TheVue!\n"
},
{
	"uri": "https://b-vwj.github.io/TheVue/school-notes/government/",
	"title": "Government Notes",
	"tags": [],
	"description": "",
	"content": " Le Gouvernement Welcome to TheVue!\n"
},
{
	"uri": "https://b-vwj.github.io/TheVue/school-notes/mathematics/",
	"title": "Math Notes",
	"tags": [],
	"description": "",
	"content": " Les Mathematiques Welcome to TheVue!\n"
},
{
	"uri": "https://b-vwj.github.io/TheVue/school-notes/",
	"title": "School Notes",
	"tags": [],
	"description": "",
	"content": " School Notes Welcome to TheVue!\n"
},
{
	"uri": "https://b-vwj.github.io/TheVue/school-notes/science/",
	"title": "Science Notes",
	"tags": [],
	"description": "",
	"content": " La Science Welcome to TheVue!\n"
},
{
	"uri": "https://b-vwj.github.io/TheVue/",
	"title": "Welcome to TheVue",
	"tags": [],
	"description": "",
	"content": " TheVue Welcome to TheVue!\n"
},
{
	"uri": "https://b-vwj.github.io/TheVue/school-notes/mathematics/college-algebra-and-trig/homework/chapter3_hw/",
	"title": "College Algebra and Pre-calculus Homework",
	"tags": [],
	"description": "Homework in here...",
	"content": "Homework for Chapter 3\nSection 3.1 Read pages 250–261 On pages 261-262 work problems 13, 17, 21, 23, 25, 29, 31, 4\nSection 3.2 Read pages 265–270 On pages 270–271 work problems 1, 7, 9, 13, 17, 19, 23, 25, 27, 29, 31, 33, 37, 39, 41, 43, 47, 53, 57, 63, 65\nSection 3.3 Read pages 272–279 On pages 279–280 work problems 1, 5, 7, 9, 11, 13, 17, 21, 25, 33, 37, 39, 41, 45, 49, 53, 57\nSection 3.4 Read pages 285–289 On pages 289–290 work problems 13, 15, 17, 21, 25, 29, 33, 37, 41, 57, 61, 65, 69\nSection 3.5 Read pages 291–298 On pages 298–299 work problems 13, 15, 21, 31, 35, 37, 39, 43, 45, 47, 49, 53, 55\nSection 3.6 Read pages 299–312 On page 313 work problems 5, 9, 15, 17, 19, 21, 33, 41, 45, 49, 57, 61\n"
},
{
	"uri": "https://b-vwj.github.io/TheVue/_footer/",
	"title": "",
	"tags": [],
	"description": "",
	"content": "Brandon Vue © 2020\n"
},
{
	"uri": "https://b-vwj.github.io/TheVue/_header/",
	"title": "",
	"tags": [],
	"description": "",
	"content": "TheVue\n"
},
{
	"uri": "https://b-vwj.github.io/TheVue/categories/",
	"title": "Categories",
	"tags": [],
	"description": "",
	"content": ""
},
{
	"uri": "https://b-vwj.github.io/TheVue/tags/",
	"title": "Tags",
	"tags": [],
	"description": "",
	"content": ""
}]